README.txt
setup.py
inetss/__init__.py
inetss/django/__init__.py
inetss/django/models.py
inetss/django/templatetags/__init__.py
inetss/django/templatetags/russian.py
ispl.egg-info/PKG-INFO
ispl.egg-info/SOURCES.txt
ispl.egg-info/dependency_links.txt
ispl.egg-info/not-zip-safe
ispl.egg-info/top_level.txt