Metadata-Version: 1.1
Name: ispl
Version: 0.0.1
Summary: Internet Services Python Library
Home-page: https://github.com/inetss/ispl
Author: Ilya Semenov
Author-email: semenov@inetss.com
License: BSD
Platform: any
Classifier: Intended Audience :: Developers
Classifier: Intended Audience :: Information Technology
Classifier: License :: OSI Approved :: BSD License
Classifier: Operating System :: OS Independent
Classifier: Programming Language :: Python
Classifier: Topic :: Software Development :: Libraries :: Python Modules
Classifier: Topic :: Internet
Classifier: Topic :: Scientific/Engineering
